README.md
flask_ecstatic.py
setup.py
Flask_Ecstatic.egg-info/PKG-INFO
Flask_Ecstatic.egg-info/SOURCES.txt
Flask_Ecstatic.egg-info/dependency_links.txt
Flask_Ecstatic.egg-info/namespace_packages.txt
Flask_Ecstatic.egg-info/requires.txt
Flask_Ecstatic.egg-info/top_level.txt
Flask_Ecstatic.egg-info/zip-safe