Metadata-Version: 1.1
Name: Flask-Ecstatic
Version: 0.3.0
Summary: Serves static files with optional directory index
Home-page: https://github.com/salsita/flask-ecstatic
Author: Salsita Software
Author-email: python@salsitasoft.com
License: MIT
Download-URL: https://github.com/salsita/flask-ecstatic/tarball/v0.3.0
Keywords: flask,static
Platform: any
Classifier: Development Status :: 4 - Beta
Classifier: Environment :: Web Environment
Classifier: Framework :: Flask
Classifier: Operating System :: OS Independent
Classifier: Intended Audience :: Developers
Classifier: Programming Language :: Python
Classifier: Programming Language :: Python :: 2.6
Classifier: Programming Language :: Python :: 2.7
Classifier: Programming Language :: Python :: 3.3
Classifier: Programming Language :: Python :: 3.4
Classifier: License :: OSI Approved :: MIT License
Classifier: Topic :: Internet :: WWW/HTTP :: Dynamic Content
Classifier: Topic :: Software Development :: Libraries :: Python Modules
